panda_producer/__init__.py
panda_producer-0.1.1.dist-info/LICENSE
panda_producer-0.1.1.dist-info/METADATA
panda_producer-0.1.1.dist-info/WHEEL
panda_producer-0.1.1.dist-info/top_level.txt
panda_producer-0.1.1.dist-info/RECORD
