Metadata-Version: 2.1
Name: panda-producer
Version: 0.1.1
Summary: put panda on your head
Home-page: https://https://gitee.com/zhao_qy/panda_producer
Author: Autumn
Author-email: zhao_qyu@163.com
License: MIT
Platform: UNKNOWN
Classifier: Programming Language :: Python :: 3
Classifier: Programming Language :: Python :: 3.5
Classifier: Programming Language :: Python :: 3.5
Classifier: Programming Language :: Python :: 3.6
Classifier: Programming Language :: Python :: 3.7
Requires-Dist: numpy
Requires-Dist: opencv-python
